spotify2ytmusicv2/__init__.py
spotify2ytmusicv2/__main__.py
spotify2ytmusicv2/backend.py
spotify2ytmusicv2/cli.py
spotify2ytmusicv2/gui.py
spotify2ytmusicv2/reverse_playlist.py
spotify2ytmusicv2/settings.json
spotify2ytmusicv2/spotify_backup.py
spotify2ytmusicv2/ytmusic_credentials.py
spotify2ytmusicv2-0.2.2.dist-info/entry_points.txt
spotify2ytmusicv2-0.2.2.dist-info/LICENSE
spotify2ytmusicv2-0.2.2.dist-info/METADATA
spotify2ytmusicv2-0.2.2.dist-info/WHEEL
spotify2ytmusicv2-0.2.2.dist-info/RECORD
